pyurt/__init__.py
urt/__init__.py
urt-0.1.3.data/scripts/urt
urt-0.1.3.dist-info/DESCRIPTION.rst
urt-0.1.3.dist-info/METADATA
urt-0.1.3.dist-info/RECORD
urt-0.1.3.dist-info/WHEEL
urt-0.1.3.dist-info/metadata.json
urt-0.1.3.dist-info/top_level.txt
