Metadata-Version: 2.0
Name: urt
Version: 0.1.3
Summary: Urban Terror Server Monitor
Home-page: http://github.com/masnun/urt
Author: Abu Ashraf Masnun
Author-email: masnun@gmail.com
License: MIT
Platform: UNKNOWN
Requires-Dist: urwid
